[
  {
    "id": 1,
    "name": "Story Book",
    "title": "Lorem ipsum dolor sit amet consectetur adipisicing elit.",
    "price": 0,
    "category": "Free",
    "image": "https://unsplash.com/photos/white-and-brown-book-on-brown-woven-surface-LUGuCtvlk1Q"
  },

  {
    "id": 2,
    "name": "Story Book",
    "title": "Lorem ipsum dolor sit amet consectetur adipisicing elit.",
    "price": 0,
    "category": "Free",
    "image": "https://unsplash.com/photos/white-and-brown-book-on-brown-woven-surface-LUGuCtvlk1Q"
  },

  {
    "id": 3,
    "name": "Music Book",
    "title": "Lorem ipsum dolor sit amet consectetur adipisicing elit.",
    "price": 120,
    "category": "Song",
    "image": "https://unsplash.com/photos/white-and-brown-book-on-brown-woven-surface-LUGuCtvlk1Q"
  },

  {
    "id": 4,
    "name": "Science Book",
    "title": "Lorem ipsum dolor sit amet consectetur adipisicing elit.",
    "price": 120,
    "category": "Science",
    "image": "https://unsplash.com/photos/white-and-brown-book-on-brown-woven-surface-LUGuCtvlk1Q"
  },

  {
    "id": 5,
    "name": "Mystery Book",
    "title": "Lorem ipsum dolor sit amet consectetur adipisicing elit.",
    "price": 99,
    "category": "Mystery",
    "image": "https://unsplash.com/photos/white-and-brown-book-on-brown-woven-surface-LUGuCtvlk1Q"
  },

  {
    "id": 6,
    "name": "Story Book",
    "title": "Lorem ipsum dolor sit amet consectetur adipisicing elit.",
    "price": 0,
    "category": "Free",
    "image": "https://unsplash.com/photos/white-and-brown-book-on-brown-woven-surface-LUGuCtvlk1Q"
  },

  {
    "id": 7,
    "name": "Fiction Book",
    "title": "Lorem ipsum dolor sit amet consectetur adipisicing elit.",
    "price": 199,
    "category": "Fiction",
    "image": "https://unsplash.com/photos/white-and-brown-book-on-brown-woven-surface-LUGuCtvlk1Q"
  },

  {
    "id": 8,
    "name": "Ghost Book",
    "title": "Lorem ipsum dolor sit amet consectetur adipisicing elit.",
    "price": 0,
    "category": "Free",
    "image": "https://unsplash.com/photos/white-and-brown-book-on-brown-woven-surface-LUGuCtvlk1Q"
  }
]
